flexceptions/__init__.py
flexceptions/core_exceptions/__init__.py
flexceptions/core_exceptions/base_exceptions.py
flexceptions/core_exceptions/wrapped_exceptions.py
flexceptions/decorators/__init__.py
flexceptions/decorators/exceptions_decorators.py
flexceptions/handlers/__init__.py
flexceptions/handlers/handlers_typing.py
Flexceptions-1.0.0.dist-info/LICENSE
Flexceptions-1.0.0.dist-info/METADATA
Flexceptions-1.0.0.dist-info/WHEEL
Flexceptions-1.0.0.dist-info/top_level.txt
Flexceptions-1.0.0.dist-info/RECORD
