Metadata-Version: 2.1
Name: Flexceptions
Version: 1.0.0
Summary: Python Flexible Exceptions Library
Home-page: https://github.com/AlejandroCabeza/flexceptions/
Author: Alejandro Cabeza Romero
Author-email: alex@alexcabeza.io
License: UNKNOWN
Platform: UNKNOWN
Classifier: Intended Audience :: Developers
Classifier: Operating System :: OS Independent
Classifier: Programming Language :: Python
Classifier: Programming Language :: Python :: 3 :: Only
Classifier: Programming Language :: Python :: 3.8
Classifier: Programming Language :: Python :: 3.9
Classifier: Programming Language :: Python :: 3.10
Requires-Python: >=3.8
License-File: LICENSE
